backports/__init__.py
backports/shutil_which.py
backports.shutil_which-3.5.2.dist-info/METADATA
backports.shutil_which-3.5.2.dist-info/RECORD
backports.shutil_which-3.5.2.dist-info/WHEEL
